cmsplugin_pagebreaks/__init__.py
cmsplugin_pagebreaks/cms_plugins.py
cmsplugin_pagebreaks/models.py
cmsplugin_pagebreaks/settings.py
cmsplugin_pagebreaks/locale/pl/LC_MESSAGES/django.mo
cmsplugin_pagebreaks/locale/pl/LC_MESSAGES/django.po
cmsplugin_pagebreaks/migrations/0001_initial.py
cmsplugin_pagebreaks/migrations/__init__.py
cmsplugin_pagebreaks/templates/cms/.DS_Store
cmsplugin_pagebreaks/templates/cms/plugins/page-break-page.html
cmsplugin_pagebreaks/templates/cms/plugins/page-break.html
cmsplugin_pagebreaks-0.1.1.dist-info/DESCRIPTION.rst
cmsplugin_pagebreaks-0.1.1.dist-info/METADATA
cmsplugin_pagebreaks-0.1.1.dist-info/RECORD
cmsplugin_pagebreaks-0.1.1.dist-info/WHEEL
cmsplugin_pagebreaks-0.1.1.dist-info/metadata.json
cmsplugin_pagebreaks-0.1.1.dist-info/top_level.txt
